typeclass/__init__.py
typeclass/typeclass.py
typeclass-0.1.2.dist-info/METADATA
typeclass-0.1.2.dist-info/WHEEL
typeclass-0.1.2.dist-info/RECORD
