Metadata-Version: 2.1
Name: typeclass
Version: 0.1.2
Summary: A small Python package that adds typeclasses
License: MIT
Author: Xpo Development
Author-email: dev@xpo.dev
Requires-Python: >=3.7,<4.0
Classifier: License :: OSI Approved :: MIT License
Classifier: Programming Language :: Python :: 3
Classifier: Programming Language :: Python :: 3.7
Classifier: Programming Language :: Python :: 3.8
Classifier: Programming Language :: Python :: 3.9
Classifier: Programming Language :: Python :: 3.10
Classifier: Programming Language :: Python :: 3.11
Requires-Dist: extype (>=1.1.1,<2.0.0)
